tkile/Constant.py
tkile/Icons.py
tkile/__init__.py
Tklie-0.0.1.dev3.dist-info/METADATA
Tklie-0.0.1.dev3.dist-info/WHEEL
Tklie-0.0.1.dev3.dist-info/top_level.txt
Tklie-0.0.1.dev3.dist-info/RECORD
